adapters/__init__.py
adapters/cmsis_nn/__init__.py
adapters/cmsis_nn/adapter.py
estimators/__init__.py
estimators/memory_estimator.py
miniml/__init__.py
miniml/ml_compat.py
miniml/ml_exporter.py
miniml/ml_factory.py
miniml/ml_manager.py
miniml/ml_runtime.py
miniml_engine-1.0.2.dist-info/licenses/LICENSE
miniml_engine-1.0.2.dist-info/METADATA
miniml_engine-1.0.2.dist-info/WHEEL
miniml_engine-1.0.2.dist-info/top_level.txt
miniml_engine-1.0.2.dist-info/RECORD
