Metadata-Version: 2.4
Name: miniml-engine
Version: 1.0.2
Summary: A lightweight, dependency-free Machine Learning framework for Embedded Systems
Author-email: Michego Takoro <tmichego@gmail.com>
License: MIT License
Project-URL: Homepage, https://github.com/Shuuida/MiniML-Engine
Project-URL: Bug Tracker, https://github.com/Shuuida/MiniML-Engine/issues
Classifier: Programming Language :: Python :: 3
Classifier: License :: OSI Approved :: MIT License
Classifier: Operating System :: OS Independent
Classifier: Topic :: Scientific/Engineering :: Artificial Intelligence
Classifier: Topic :: Software Development :: Embedded Systems
Classifier: Intended Audience :: Developers
Classifier: Intended Audience :: Education
Requires-Python: >=3.7
License-File: LICENSE
Provides-Extra: faster-training
Requires-Dist: scikit-learn>=1.0.0; extra == "faster-training"
Requires-Dist: numpy; extra == "faster-training"
Requires-Dist: scipy; extra == "faster-training"
Dynamic: license-file
Dynamic: requires-python
